{"<cs>,my": 5, "my,lords": 5, "lords,i": 4, "i,am": 4, "am,greatly": 1, "greatly,heartened": 1, "heartened,by": 1, "by,the": 2, "the,support": 1, "support,which": 1, "which,has": 1, "has,been": 1, "been,given": 1, "given,to": 1, "to,the": 2, "the,<e>": 1, "am,grateful": 2, "grateful,to": 2, "to,my": 1, "my,noble": 1, "noble,friend": 1, "friend,lord": 1, "lord,boyd-carpenter": 1, "boyd-carpenter,for": 1, "for,intiating": 1, "intiating,the": 1, "the,debate": 1, "debate,this": 1, "this,afternoon": 1, "afternoon,and": 1, "and,for": 1, "for,his": 1, "his,thoughtful": 1, "thoughtful,contribution": 1, "contribution,<e>": 1, "<e>,<s>": 15, "<s>,it": 2, "it,was": 1, "was,right": 1, "right,that": 1, "that,he": 1, "he,should": 1, "should,remind": 1, "remind,us": 1, "us,that": 1, "that,jobs": 1, "jobs,go": 1, "go,with": 1, "with,customers": 1, "customers,<e>": 1, "<s>,i": 3, "i,was": 1, "was,also": 1, "also,interested": 1, "interested,in": 1, "in,his": 1, "his,reminder": 1, "reminder,of": 1, "of,the": 5, "the,political": 1, "political,affiliation": 2, "affiliation,or": 1, "or,rather": 1, "rather,the": 1, "the,lack": 1, "lack,of": 1, "of,political": 1, "affiliation,of": 1, "of,labour": 1, "labour,unions": 1, "unions,in": 2, "in,the": 3, "the,united": 1, "united,states": 1, "states,of": 1, "of,america": 1, "america,<e>": 1, "it,sometimes": 1, "sometimes,occurs": 1, "occurs,to": 1, "to,me": 1, "me,to": 1, "to,ask": 1, "ask,how": 1, "how,well": 1, "well,the": 1, "the,leadership": 1, "leadership,of": 1, "of,unions": 1, "in,this": 1, "this,country": 1, "country,today": 1, "today,reflects": 1, "reflects,the": 1, "the,real": 1, "real,political": 1, "political,views": 1, "views,of": 1, "the,members": 1, "members,because": 1, "because,i": 1, "i,think": 1, "think,there": 1, "there,is": 2, "is,a": 2, "a,connection": 1, "connection,with": 1, "with,the": 1, "the,decline": 1, "decline,of": 1, "of,membership": 1, "membership,which": 1, "which,we": 1, "we,have": 3, "have,seen": 1, "seen,in": 1, "in,recent": 1, "recent,years": 1, "years,<e>": 1, "<s>,however": 1, "however,that": 1, "that,is": 2, "is,not": 1, "not,the": 1, "the,subject": 1, "subject,for": 1, "for,today": 1, "today,<e>": 1, "lords,through": 1, "through,perseverance": 1, "perseverance,and": 1, "and,hard": 1, "hard,work": 1, "work,<e>": 1, "<s>,hopefully": 1, "hopefully,the": 1, "the,public": 1, "public,will": 1, "will,begin": 1, "begin,to": 1, "to,realise": 1, "realise,that": 1, "that,many": 1, "many,of": 1, "the,problems": 1, "problems,which": 1, "which,have": 1, "have,been": 1, "been,undertaken": 1, "undertaken,and": 1, "and,looked": 1, "looked,at": 1, "at,in": 1, "in,respect": 1, "respect,of": 1, "the,first": 1, "first,pwr": 1, "pwr,inquiry": 1, "inquiry,will": 1, "will,not": 1, "not,have": 1, "have,to": 2, "to,be": 1, "be,repeated": 1, "repeated,every": 1, "every,single": 2, "single,time": 1, "time,at": 1, "at,every": 1, "single,inquiry": 1, "inquiry,<e>": 1, "<s>,there": 1, "is,no": 1, "no,other": 1, "other,way": 1, "way,and": 1, "and,we": 1, "to,do": 1, "do,two": 1, "two,things": 1, "things,first": 1, "first,provide": 1, "provide,planning": 1, "planning,permissions": 1, "permissions,in": 1, "in,order": 2, "order,to": 1, "to,get": 1, "get,these": 1, "these,built": 1, "built,and": 1, "and,secondly": 1, "secondly,make": 1, "make,sure": 1, "sure,that": 1, "that,finance": 1, "finance,is": 1, "is,available": 1, "available,<e>": 2, "<s>,one": 1, "one,of": 1, "the,reasons": 1, "reasons,we": 1, "we,are": 1, "are,looking": 1, "looking,at": 1, "at,the": 1, "the,electricity": 1, "electricity,supply": 1, "supply,industry": 1, "industry,going": 1, "going,into": 1, "into,the": 1, "the,private": 1, "private,sector": 1, "sector,is": 1, "is,in": 2, "order,that": 1, "that,more": 1, "more,methods": 1, "methods,of": 1, "of,finance": 1, "finance,should": 1, "should,be": 1, "be,available": 1, "<s>,the": 1, "the,noble": 3, "noble,lord": 3, "lord,lord": 2, "lord,dean": 1, "dean,of": 1, "of,beswick": 1, "beswick,<e>": 1, "<cs>,i": 1, "am,glad": 1, "glad,that": 1, "that,at": 1, "at,long": 1, "long,last": 1, "last,i": 1, "i,can": 1, "can,satisfy": 1, "satisfy,noble": 1, "noble,lords": 1, "lords,opposite": 1, "opposite,<e>": 1, "<s>,we": 1, "have,given": 1, "given,this": 1, "this,matter": 1, "matter,a": 1, "a,great": 1, "great,deal": 1, "deal,of": 1, "of,consideration": 1, "consideration,since": 1, "since,the": 1, "the,white": 1, "white,paper": 1, "paper,was": 1, "was,published": 1, "published,and": 1, "and,that": 1, "that,has": 1, "has,enabled": 1, "enabled,us": 1, "us,to": 1, "to,see": 1, "see,the": 1, "the,underlying": 1, "underlying,principles": 1, "principles,more": 1, "more,clearly": 1, "clearly,<e>": 1, "<s>,practical": 1, "practical,difficulties": 1, "difficulties,have": 1, "have,also": 1, "also,become": 1, "become,more": 1, "more,apparent": 1, "apparent,with": 1, "with,time": 1, "time,particularly": 1, "particularly,in": 1, "the,light": 1, "light,of": 1, "of,our": 1, "our,considerable": 1, "considerable,but": 1, "but,unsuccessful": 1, "unsuccessful,efforts": 1, "efforts,to": 1, "to,establish": 1, "establish,a": 1, "a,satisfactory": 1, "satisfactory,rebate": 1, "rebate,scheme": 1, "scheme,for": 1, "for,blind": 1, "blind,people": 1, "people,to": 1, "to,which": 1, "which,i": 1, "i,have": 1, "have,already": 1, "already,referred": 1, "referred,<e>": 1, "lord,williams": 1, "williams,although": 1, "although,i": 1, "i,confess": 1, "confess,that": 1, "that,i": 1, "i,found": 1, "found,it": 1, "it,rather": 1, "rather,difficult": 1, "difficult,to": 1, "to,follow": 1, "follow,him": 1, "him,<e>": 1, "<s>,he": 1, "he,started": 1, "started,by": 1, "by,saying": 2, "saying,that": 2, "that,father": 1, "father,christmas": 1, "christmas,had": 1, "had,come": 1, "come,to": 1, "to,british": 1, "british,aerospace": 1, "aerospace,and": 1, "and,concluded": 1, "concluded,by": 1, "that,the": 1, "the,deal": 1, "deal,would": 1, "would,undermine": 1, "undermine,its": 1, "its,whole": 1, "whole,future": 1, "future,<e>": 1, "i,believe": 1, "believe,that": 1, "that,this": 1, "this,is": 1, "a,well-balanced": 1, "well-balanced,deal": 1, "deal,<e>": 1, "i,know": 1, "know,of": 1, "of,no": 1, "no,such": 1, "such,department": 1, "department,<e>": 1, "<s>,all": 1, "all,advertisements": 1, "advertisements,that": 1, "that,appear": 1, "appear,on": 1, "on,television": 1, "television,must": 1, "must,be": 1, "be,approved": 1, "approved,by": 1, "the,iba": 1, "iba,as": 1, "as,the": 1, "the,government": 1, "government,found": 1, "found,in": 1, "the,s": 1, "s,and": 1, "and,early": 1, "early,s": 1, "s,<e>": 1, "i,cannot": 1, "cannot,find": 1, "find,one": 1, "one,thing": 1, "thing,in": 1, "in,anything": 1, "anything,that": 1, "that,my": 1, "my,department": 1, "department,advertises": 1, "advertises,that": 1, "is,the": 1, "the,remotest": 1, "remotest,bit": 1, "bit,political": 1, "political,unless": 1, "unless,the": 1, "lord,thinks": 1, "thinks,that": 1, "that,describing": 1, "describing,cases": 1, "cases,of": 1, "of,success": 1, "success,in": 1, "in,consett": 1, "consett,the": 1, "the,lake": 1, "lake,district": 1, "district,yorkshire": 1, "yorkshire,portsmouth": 1, "portsmouth,cornwall": 1, "cornwall,kent": 1, "kent,corby": 1, "corby,scunthorpe": 1, "scunthorpe,and": 1, "and,even": 1, "even,london": 1, "london,is": 1, "is,political": 1, "political,<e>": 1, "<s>,if": 1, "if,so": 1, "so,he": 1, "he,is": 1, "in,danger": 1, "danger,of": 1, "of,aligning": 1, "aligning,the": 1, "the,labour": 1, "labour,party": 1, "party,with": 1, "with,failure": 1, "failure,<e>": 1}