{"<cs>,my,lords": 6, "my,lords,speaking": 1, "lords,speaking,as": 1, "speaking,as,one": 1, "as,one,of": 1, "one,of,your": 1, "of,your,lordships": 1, "your,lordships,who": 1, "lordships,who,has": 1, "who,has,lived": 1, "has,lived,next": 1, "lived,next,door": 1, "next,door,to": 1, "door,to,the": 1, "to,the,chemical": 1, "the,chemical,warfare": 1, "chemical,warfare,establishment": 1, "warfare,establishment,for": 1, "establishment,for,some": 1, "for,some,years": 1, "some,years,may": 1, "years,may,i": 1, "may,i,ask": 1, "i,ask,whether": 1, "ask,whether,the": 1, "whether,the,minister": 1, "the,minister,is": 1, "minister,is,aware": 1, "is,aware,that": 1, "aware,that,in": 1, "that,in,fact": 1, "in,fact,we": 1, "fact,we,are": 1, "we,are,as": 1, "are,as,much": 1, "as,much,up": 1, "much,up,to": 1, "up,to,date": 1, "to,date,now": 1, "date,now,as": 1, "now,as,we": 1, "as,we,can": 1, "we,can,find": 1, "can,find,out": 1, "find,out,the": 1, "out,the,situation": 1, "the,situation,in": 1, "situation,in,any": 1, "in,any,local": 1, "any,local,pub": 1, "local,pub,in": 1, "pub,in,the": 1, "in,the,wiltshire": 1, "the,wiltshire,area": 1, "wiltshire,area,that": 1, "area,that,we": 1, "that,we,go": 1, "we,go,into": 1, "go,into,as": 1, "into,as,we": 1, "as,we,have": 1, "we,have,ever": 1, "have,ever,been": 1, "ever,been,<e>": 1, "my,lords,psychopathic": 1, "lords,psychopathic,disorder": 1, "psychopathic,disorder,is": 2, "disorder,is,an": 1, "is,an,extremely": 1, "an,extremely,difficult": 1, "extremely,difficult,disorder": 1, "difficult,disorder,to": 1, "disorder,to,diagnose": 1, "to,diagnose,<e>": 1, "diagnose,<e>,<s>": 1, "<e>,<s>,i": 2, "<s>,i,personally": 1, "i,personally,think": 1, "personally,think,that": 1, "think,that,if": 1, "that,if,one": 1, "if,one,puts": 1, "one,puts,it": 1, "puts,it,into": 1, "it,into,the": 1, "into,the,same": 1, "the,same,grade": 1, "same,grade,as": 1, "grade,as,a": 1, "as,a,personality": 1, "a,personality,disorder": 2, "personality,disorder,this": 1, "disorder,this,would": 1, "this,would,be": 1, "would,be,entirely": 1, "be,entirely,wrong": 1, "entirely,wrong,<e>": 1, "wrong,<e>,<s>": 1, "<e>,<s>,basically": 1, "<s>,basically,a": 1, "basically,a,personality": 1, "personality,disorder,is": 1, "disorder,is,a": 1, "is,a,neurotic": 1, "a,neurotic,condition": 1, "neurotic,condition,whereas": 1, "condition,whereas,a": 1, "whereas,a,psychopathic": 1, "a,psychopathic,disorder": 1, "disorder,is,not": 1, "is,not,though": 1, "not,though,i": 1, "though,i,quite": 1, "i,quite,agree": 1, "quite,agree,with": 1, "agree,with,what": 1, "with,what,the": 1, "what,the,noble": 1, "the,noble,lord": 3, "noble,lord,has": 1, "lord,has,said": 1, "has,said,<e>": 2, "said,<e>,<s>": 2, "<e>,<s>,it": 2, "<s>,it,is": 2, "it,is,virtually": 1, "is,virtually,impossible": 1, "virtually,impossible,to": 1, "impossible,to,treat": 1, "to,treat,<e>": 1, "treat,<e>,<s>": 1, "<e>,<s>,occasionally": 1, "<s>,occasionally,it": 1, "occasionally,it,can": 1, "it,can,<e>": 1, "my,lords,i": 4, "lords,i,should": 2, "i,should,like": 2, "should,like,very": 1, "like,very,much": 1, "very,much,to": 1, "much,to,support": 1, "to,support,the": 1, "support,the,noble": 1, "the,noble,baroness": 3, "noble,baroness,lady": 2, "baroness,lady,masham": 1, "lady,masham,in": 1, "masham,in,what": 1, "in,what,she": 1, "what,she,has": 1, "she,has,said": 1, "<e>,<s>,one": 1, "<s>,one,point": 1, "one,point,which": 1, "point,which,the": 1, "which,the,noble": 1, "noble,baroness,has": 1, "baroness,has,already": 1, "has,already,mentioned": 1, "already,mentioned,concerns": 1, "mentioned,concerns,the": 1, "concerns,the,question": 1, "the,question,of": 1, "question,of,people": 1, "of,people,who": 1, "people,who,are": 1, "who,are,on": 1, "are,on,drugs": 1, "on,drugs,coming": 1, "drugs,coming,out": 1, "coming,out,of": 2, "out,of,mental": 2, "of,mental,hospital": 1, "mental,hospital,<e>": 1, "hospital,<e>,<s>": 1, "<e>,<s>,these": 1, "<s>,these,days": 1, "these,days,they": 1, "days,they,are": 1, "they,are,nearly": 1, "are,nearly,always": 1, "nearly,always,people": 1, "always,people,who": 1, "people,who,have": 1, "who,have,suffered": 1, "have,suffered,from": 1, "suffered,from,bad": 1, "from,bad,mental": 1, "bad,mental,illness": 1, "mental,illness,and": 1, "illness,and,who": 1, "and,who,will": 1, "who,will,probably": 1, "will,probably,be": 1, "probably,be,on": 1, "be,on,drugs": 1, "on,drugs,certainly": 1, "drugs,certainly,for": 1, "certainly,for,a": 1, "for,a,year": 1, "a,year,after": 1, "year,after,discharge": 1, "after,discharge,<e>": 1, "lords,i,shall": 1, "i,shall,not": 1, "shall,not,keep": 1, "not,keep,the": 1, "keep,the,noble": 1, "noble,lord,lord": 2, "lord,lord,elton": 1, "lord,elton,for": 1, "elton,for,more": 1, "for,more,than": 1, "more,than,a": 1, "than,a,moment": 1, "a,moment,or": 1, "moment,or,two": 1, "or,two,<e>": 1, "two,<e>,<s>": 1, "<e>,<s>,however": 1, "<s>,however,during": 1, "however,during,the": 1, "during,the,last": 1, "the,last,stage": 1, "last,stage,of": 1, "stage,of,this": 1, "of,this,bill": 1, "this,bill,i": 1, "bill,i,did": 1, "i,did,talk": 1, "did,talk,about": 1, "talk,about,the": 1, "about,the,strain": 1, "the,strain,on": 1, "strain,on,patients": 1, "on,patients,coming": 1, "patients,coming,out": 1, "of,mental,<e>": 1, "lords,i,believe": 1, "i,believe,that": 1, "believe,that,the": 1, "that,the,noble": 1, "baroness,lady,faithfull": 1, "lady,faithfull,is": 1, "faithfull,is,on": 1, "is,on,to": 1, "on,to,a": 1, "to,a,winner": 1, "a,winner,in": 1, "winner,in,suggesting": 1, "in,suggesting,the": 1, "suggesting,the,possibility": 1, "the,possibility,of": 1, "possibility,of,turning": 1, "of,turning,the": 1, "turning,the,wards": 1, "the,wards,of": 1, "wards,of,mental": 1, "of,mental,hospitals": 1, "mental,hospitals,into": 1, "hospitals,into,accommodation": 1, "into,accommodation,where": 1, "accommodation,where,prostitutes": 1, "where,prostitutes,and": 1, "prostitutes,and,alcoholics": 1, "and,alcoholics,can": 1, "alcoholics,can,be": 1, "can,be,sent": 1, "be,sent,<e>": 1, "sent,<e>,<s>": 1, "it,is,no": 1, "is,no,good": 1, "no,good,putting": 1, "good,putting,them": 1, "putting,them,in": 1, "them,in,prison": 1, "in,prison,<e>": 1, "prison,<e>,<s>": 1, "<s>,i,am": 1, "i,am,convinced": 1, "am,convinced,that": 1, "convinced,that,probably": 1, "that,probably,with": 1, "probably,with,a": 1, "with,a,little": 1, "a,little,thought": 1, "little,thought,it": 1, "thought,it,would": 1, "it,would,be": 1, "would,be,possible": 1, "be,possible,to": 1, "possible,to,have": 1, "to,have,such": 1, "have,such,people": 1, "such,people,transferred": 1, "people,transferred,to": 1, "transferred,to,these": 1, "to,these,wards": 1, "these,wards,which": 1, "wards,which,at": 1, "which,at,the": 1, "at,the,moment": 1, "the,moment,are": 1, "moment,are,closed": 1, "are,closed,down": 1, "closed,down,<e>": 1, "should,like,to": 1, "like,to,congratulate": 1, "to,congratulate,the": 1, "congratulate,the,noble": 1, "lord,lord,mackie": 1, "lord,mackie,of": 1, "mackie,of,benshie": 1, "of,benshie,on": 1, "benshie,on,<e>": 1}