{"<cs>,my,lords": 4, "my,lords,i": 2, "lords,i,have": 1, "i,have,just": 1, "have,just,exercised": 1, "just,exercised,my": 1, "exercised,my,choice": 1, "my,choice,to": 1, "choice,to,vote": 1, "to,vote,against": 1, "vote,against,my": 1, "against,my,party": 1, "my,party,<e>": 1, "party,<e>,<s>": 1, "<e>,<s>,i": 4, "<s>,i,should": 1, "i,should,like": 1, "should,like,to": 1, "like,to,support": 1, "to,support,this": 1, "support,this,amendment": 1, "this,amendment,very": 1, "amendment,very,strongly": 1, "very,strongly,indeed": 1, "strongly,indeed,<e>": 1, "indeed,<e>,<s>": 1, "<e>,<s>,it": 1, "<s>,it,is": 1, "it,is,extremely": 1, "is,extremely,well": 1, "extremely,well,phrased": 1, "well,phrased,every": 1, "phrased,every,part": 1, "every,part,of": 1, "part,of,it": 1, "of,it,carries": 1, "it,carries,weight": 1, "carries,weight,<e>": 1, "weight,<e>,<s>": 1, "<s>,i,hope": 1, "i,hope,that": 1, "hope,that,the": 1, "that,the,government": 1, "the,government,will": 1, "government,will,give": 1, "will,give,it": 1, "give,it,their": 1, "it,their,very": 1, "their,very,serious": 1, "very,serious,consideration": 1, "serious,consideration,and": 1, "consideration,and,include": 1, "and,include,it": 1, "include,it,in": 1, "it,in,the": 1, "in,the,bill": 1, "the,bill,<e>": 1, "lords,i,wonder": 1, "i,wonder,if": 1, "wonder,if,i": 1, "if,i,may": 1, "i,may,make": 1, "may,make,an": 1, "make,an,observation": 1, "an,observation,on": 1, "observation,on,this": 1, "on,this,amendment": 1, "this,amendment,although": 1, "amendment,although,it": 1, "although,it,may": 1, "it,may,not": 1, "may,not,be": 1, "not,be,too": 1, "be,too,happily": 1, "too,happily,received": 1, "happily,received,by": 1, "received,by,my": 1, "by,my,colleagues": 1, "my,colleagues,on": 1, "colleagues,on,the": 1, "on,the,front": 1, "the,front,bench": 1, "front,bench,<e>": 1, "bench,<e>,<s>": 1, "<s>,i,point": 1, "i,point,out": 1, "point,out,that": 1, "out,that,i": 1, "that,i,have": 2, "i,have,had": 1, "have,had,the": 1, "had,the,experience": 1, "the,experience,of": 1, "experience,of,teaching": 1, "of,teaching,in": 1, "teaching,in,a": 1, "in,a,school": 1, "a,school,for": 1, "school,for,the": 1, "for,the,maladjusted": 1, "the,maladjusted,where": 1, "maladjusted,where,the": 1, "where,the,ratio": 1, "the,ratio,of": 1, "ratio,of,teachers": 1, "of,teachers,to": 1, "teachers,to,children": 1, "to,children,is": 1, "children,is,much": 1, "is,much,higher": 1, "much,higher,than": 1, "higher,than,it": 1, "than,it,is": 1, "it,is,for": 1, "is,for,example": 1, "for,example,in": 1, "example,in,a": 1, "in,a,grammar": 1, "a,grammar,school": 1, "grammar,school,<e>": 1, "school,<e>,<s>": 1, "<e>,<s>,therefore": 1, "<s>,therefore,to": 1, "therefore,to,infer": 1, "to,infer,that": 1, "infer,that,a": 1, "that,a,higher": 1, "a,higher,capitation": 1, "higher,capitation,charge": 1, "capitation,charge,on": 1, "charge,on,grammar": 1, "on,grammar,school": 1, "grammar,school,children": 1, "school,children,is": 1, "children,is,necessarily": 1, "is,necessarily,a": 1, "necessarily,a,sign": 1, "a,sign,that": 1, "sign,that,more": 1, "that,more,is": 1, "more,is,being": 1, "is,being,spent": 1, "being,spent,on": 1, "spent,on,the": 1, "on,the,more": 1, "the,more,intelligent": 1, "more,intelligent,children": 1, "intelligent,children,than": 1, "children,than,on": 1, "than,on,children": 1, "on,children,of": 1, "children,of,lower": 1, "of,lower,intelligence": 1, "lower,intelligence,is": 1, "intelligence,is,not": 1, "is,not,necessarily": 1, "not,necessarily,right": 1, "necessarily,right,<e>": 1, "my,lords,before": 1, "lords,before,the": 1, "before,the,noble": 1, "the,noble,lord": 1, "noble,lord,sits": 1, "lord,sits,down": 1, "sits,down,may": 1, "down,may,i": 1, "may,i,add": 1, "i,add,something": 1, "add,something,to": 1, "something,to,what": 1, "to,what,he": 1, "what,he,has": 1, "he,has,just": 1, "has,just,said": 1, "just,said,<e>": 1, "said,<e>,<s>": 1, "<e>,<s>,he": 2, "<s>,he,said": 1, "he,said,that": 1, "said,that,the": 1, "that,the,conservative": 1, "the,conservative,party": 1, "conservative,party,had": 1, "party,had,a": 2, "had,a,contingent": 1, "a,contingent,in": 1, "contingent,in,the": 1, "in,the,march": 1, "the,march,on": 1, "march,on,saturday": 1, "on,saturday,<e>": 1, "saturday,<e>,<s>": 1, "<s>,he,did": 1, "he,did,not": 1, "did,not,mention": 1, "not,mention,that": 1, "mention,that,the": 1, "that,the,liberal": 1, "the,liberal,party": 1, "liberal,party,had": 1, "had,a,very": 1, "a,very,much": 1, "very,much,larger": 1, "much,larger,contingent": 1, "larger,contingent,<e>": 1, "my,lords,it": 1, "lords,it,is": 1, "it,is,some": 1, "is,some,years": 1, "some,years,since": 1, "years,since,i": 1, "since,i,made": 1, "i,made,my": 1, "made,my,maiden": 1, "my,maiden,speech": 1, "maiden,speech,and": 1, "speech,and,this": 1, "and,this,is": 1, "this,is,the": 1, "is,the,first": 1, "the,first,speech": 1, "first,speech,that": 1, "speech,that,i": 1, "i,have,made": 1, "have,made,from": 1, "made,from,the": 1, "from,the,liberal": 1, "the,liberal,benches": 1, "liberal,benches,<e>": 1, "benches,<e>,<s>": 1, "<s>,i,am": 1, "i,am,afraid": 1, "am,afraid,my": 1, "afraid,my,colleagues": 1, "my,colleagues,will": 1, "colleagues,will,not": 1, "will,not,be": 1, "not,be,very": 1, "be,very,pleased": 1, "very,pleased,with": 1, "pleased,with,what": 1, "with,what,i": 1, "what,i,am": 1, "i,am,going": 1, "am,going,to": 1, "going,to,say": 1, "to,say,<e>": 1, "say,<e>,<s>": 1, "<e>,<s>,when": 1, "<s>,when,i": 1, "when,i,went": 1, "i,went,to": 1, "went,to,manchester": 1, "to,manchester,university": 1, "manchester,university,i": 1, "university,i,had": 1, "i,had,no": 1, "had,no,grant": 1, "no,grant,<e>": 1, "grant,<e>,<s>": 1, "<e>,<s>,my": 1, "<s>,my,father": 1, "my,father,paid": 1, "father,paid,no": 1, "paid,no,fees": 1, "no,fees,for": 1, "fees,for,me": 1, "for,me,<e>": 1, "me,<e>,<s>": 1, "<e>,<s>,what": 1, "<s>,what,i": 1, "what,i,had": 1, "i,had,to": 1, "had,to,live": 1, "to,live,on": 1, "live,on,was": 1, "on,was,the": 1, "was,the,money": 1, "the,money,that": 1, "money,that,my": 1, "that,my,wife": 1, "my,wife,earned": 1, "wife,earned,<e>": 1}